pysql_repo/__init__.py
pysql_repo/_database.py
pysql_repo/_database_base.py
pysql_repo/_decorators.py
pysql_repo/_repository.py
pysql_repo/_service.py
pysql_repo/_utils.py
pysql_repo/py.typed
pysql_repo/_constants/__init__.py
pysql_repo/_constants/enum.py
pysql_repo/asyncio/__init__.py
pysql_repo/asyncio/async_database.py
pysql_repo/asyncio/async_decorator.py
pysql_repo/asyncio/async_repository.py
pysql_repo/asyncio/async_service.py
pysql_repo/libs/__init__.py
pysql_repo/libs/file_lib.py
pysql_repo-0.7.4.0.dist-info/METADATA
pysql_repo-0.7.4.0.dist-info/WHEEL
pysql_repo-0.7.4.0.dist-info/top_level.txt
pysql_repo-0.7.4.0.dist-info/RECORD
