Metadata-Version: 2.1
Name: pysql-repo
Version: 0.7.4.0
Summary: A project to have a base repository class to perform select/insert/update/delete with dynamic syntax
Home-page: https://github.com/Impro02/pysql-repo
Download-URL: https://github.com/Impro02/pysql-repo/archive/refs/tags/0.7.4.0.tar.gz
Author: Maxime MARTIN
Author-email: Maxime MARTIN <maxime.martin02@hotmail.fr>
License: MIT
Classifier: Development Status :: 3 - Alpha
Classifier: Intended Audience :: Developers
Classifier: License :: OSI Approved :: MIT License
Classifier: Programming Language :: Python :: 3
Requires-Python: >=3.8
Requires-Dist: sqlalchemy >=2.0.0
